ai_edge_torch/__init__.py
ai_edge_torch-0.7.2.dist-info/METADATA
ai_edge_torch-0.7.2.dist-info/WHEEL
ai_edge_torch-0.7.2.dist-info/top_level.txt
ai_edge_torch-0.7.2.dist-info/RECORD
