Metadata-Version: 2.4
Name: ai-edge-torch
Version: 0.7.2
Summary: DEPRECATED: renamed to litert-torch
Classifier: Development Status :: 7 - Inactive
Requires-Dist: litert-torch
Dynamic: classifier
Dynamic: description
Dynamic: description-content-type
Dynamic: requires-dist
Dynamic: summary
